luigi_monitor/__init__.py
luigi_monitor/luigi_monitor.py
luigi_monitor-1.1.4.dist-info/DESCRIPTION.rst
luigi_monitor-1.1.4.dist-info/METADATA
luigi_monitor-1.1.4.dist-info/RECORD
luigi_monitor-1.1.4.dist-info/WHEEL
luigi_monitor-1.1.4.dist-info/entry_points.txt
luigi_monitor-1.1.4.dist-info/metadata.json
luigi_monitor-1.1.4.dist-info/top_level.txt
