Metadata-Version: 1.1
Name: luigi-monitor
Version: 1.1.4
Summary: Send summary messages of your Luigi jobs to Slack.
Home-page: https://github.com/hudl/luigi-monitor
Author: Hudl
Author-email: alex.debrie@hudl.com
License: MIT
Keywords: luigi
Platform: UNKNOWN
Classifier: Development Status :: 3 - Alpha
Classifier: Intended Audience :: Developers
Classifier: License :: OSI Approved :: MIT License
Classifier: Programming Language :: Python :: 2.7
Classifier: Programming Language :: Python :: 3.6
Classifier: Programming Language :: Python :: 3.7
